practicusai/__init__.py
practicusaicore/__init__.py
practicusnode/__init__.py
practicusnode-0.0.1.dist-info/METADATA
practicusnode-0.0.1.dist-info/WHEEL
practicusnode-0.0.1.dist-info/top_level.txt
practicusnode-0.0.1.dist-info/RECORD
