Metadata-Version: 2.1
Name: practicusnode
Version: 0.0.1
Summary: Please visit practicus.ai to learn how to use Practicus AI cloud node
Home-page: https://practicus.ai/
Author: Practicus AI
Author-email: info@practicus.ai
License: UNKNOWN
Platform: UNKNOWN
Requires-Python: >=3.10
